nbtschematic/__init__.py
nbtschematic/schematic.py
nbtschematic/version.py
nbtschematic-0.2.1.dist-info/LICENSE
nbtschematic-0.2.1.dist-info/METADATA
nbtschematic-0.2.1.dist-info/WHEEL
nbtschematic-0.2.1.dist-info/top_level.txt
nbtschematic-0.2.1.dist-info/RECORD
