Metadata-Version: 2.1
Name: nbtschematic
Version: 0.2.1
Summary: A simple schematic file reader for nbtlib
Home-page: https://github.com/cbs228/nbtschematic
Author: Colin S.
Author-email: 3526918+cbs228@users.noreply.github.com
License: MIT
Keywords: nbt schema minecraft mcschematic schematic package library
Platform: any
Classifier: Development Status :: 3 - Alpha
Classifier: Intended Audience :: Developers
Classifier: License :: OSI Approved :: MIT License
Classifier: Operating System :: OS Independent
Classifier: Programming Language :: Python :: 3.8
Classifier: Programming Language :: Python :: 3.9
Classifier: Topic :: Software Development :: Libraries :: Python Modules
Requires-Python: >=3.8
License-File: LICENSE
Requires-Dist: nbtlib (~=1.12.1)
Requires-Dist: numpy (~=1.22)
